tsqx/__about__.py
tsqx/__init__.py
tsqx/__main__.py
tsqx-1.0.0.dist-info/METADATA
tsqx-1.0.0.dist-info/WHEEL
tsqx-1.0.0.dist-info/entry_points.txt
tsqx-1.0.0.dist-info/licenses/LICENSE.md
tsqx-1.0.0.dist-info/RECORD
