Metadata-Version: 2.4
Name: tsqx
Version: 1.0.0
Summary: Asymptote pre-processor for Euclidean geometry diagrams
Project-URL: repository, https://github.com/vEnhance/tsqx/
Author-email: Evan Chen <evan@evanchen.cc>, CJ Quines <cj@cjquines.com>
License: MIT
License-File: LICENSE.md
Requires-Python: <4.0,>=3.10
Requires-Dist: prek>=0.2.25
